[{"name":"AMNESIA","artist":"WOODZ"},{"name":"Stay With Me","artist":"ASH ISLAND"},{"name":"대성 Special Single","artist":"대성"},{"name":"KINGDOM","artist":"포르테나 "},{"name":"Christmas Love","artist":"에이스 "},{"name":"Deserve","artist":"HOYA"},{"name":"Christmas Dance","artist":"ROCKY"},{"name":"Monica Bellucci","artist":"크루셜스타 "},{"name":"크리스마스에 고백","artist":"이우김한결김도희박제업최낙타"},{"name":"ROSETTA Remix ","artist":"pH-1"},{"name":"MY CHRISTMAS","artist":"HUS "},{"name":"Citi+","artist":"양홍원"},{"name":"포옹 ","artist":"선우정아"},{"name":"Miracle ","artist":"NEXZ "},{"name":"You're mine, You!","artist":"신유미"},{"name":"사랑 같은 걸 해요","artist":"화노 "},{"name":"한 번만 더 기회를 줘","artist":"박다혜"},{"name":"웰컴투 삼달리 OST Part.3","artist":"태연 "},{"name":"KWON JIN WON WITH ROB VAN BAVEL","artist":"권진원"},{"name":"보통의 외로움","artist":"모브닝 "}]